markdownpy/markdownpy.py
markdownpy-0.1.4.dist-info/LICENSE
markdownpy-0.1.4.dist-info/METADATA
markdownpy-0.1.4.dist-info/WHEEL
markdownpy-0.1.4.dist-info/top_level.txt
markdownpy-0.1.4.dist-info/RECORD
