Metadata-Version: 2.1
Name: markdownpy
Version: 0.1.4
Summary: PyPI package to write Markdown document directly from a Python script
Home-page: https://github.com/aidanjungo/Markdownpy
Author: Aidan Jungo
Author-email: aidan.jungo@cfse.ch
License: Apache License 2.0
Keywords: Markdown,Python,documentation
Classifier: Programming Language :: Python :: 3
Classifier: Programming Language :: Python :: 3.8
Classifier: Programming Language :: Python :: 3.9
Classifier: Programming Language :: Python :: 3.10
Classifier: License :: OSI Approved :: Apache Software License
Classifier: Operating System :: OS Independent
Classifier: Intended Audience :: Developers
Classifier: Topic :: Text Processing :: Markup :: Markdown
Requires-Python: >=3.8.0
License-File: LICENSE
